wopa/CT.py
wopa/LTN.py
wopa/__init__.py
wopa/tool.py
wopa-0.0.2.dist-info/LICENSE.txt
wopa-0.0.2.dist-info/METADATA
wopa-0.0.2.dist-info/WHEEL
wopa-0.0.2.dist-info/top_level.txt
wopa-0.0.2.dist-info/RECORD
