Metadata-Version: 2.1
Name: wopa
Version: 0.0.2
Summary: 一個給研究者使用的簡單便利資料搜索工具
Home-page: https://github.com/acer1456/wopa
Author: Wei
Author-email: acer1456@gmail.com
Classifier: Programming Language :: Python :: 3
Classifier: License :: OSI Approved :: MIT License
Classifier: Operating System :: OS Independent
Requires-Python: >=3.6
License-File: LICENSE.txt
Requires-Dist: requests
Requires-Dist: pandas (>=1)
Requires-Dist: newspaper3k
Requires-Dist: user-agent
Requires-Dist: xlsxwriter
